__init__.py
delete_snapshots.py
delete_volumes.py
generate_certs.py
iac_tools/__init__.py
iac_tools/clusterset.py
iac_tools/filterset.py
iac_tools/tagset.py
iac_tools/util.py
snapshot_manager.py
start_cluster.py
stop_cluster.py
tag_manager.py
ope_tools-3.1.2.dist-info/METADATA
ope_tools-3.1.2.dist-info/WHEEL
ope_tools-3.1.2.dist-info/entry_points.txt
ope_tools-3.1.2.dist-info/RECORD
