Metadata-Version: 2.3
Name: ope-tools
Version: 3.1.2
Summary: GitHub tools for Augmenting Integrations
License: AGPL-3.0-only
Author: Samuel Vange
Author-email: 7166607+svange@users.noreply.github.com
Requires-Python: >=3.10,<4.0
Classifier: License :: OSI Approved :: GNU Affero General Public License v3
Classifier: Programming Language :: Python :: 3
Classifier: Programming Language :: Python :: 3.10
Classifier: Programming Language :: Python :: 3.11
Classifier: Programming Language :: Python :: 3.12
Classifier: Programming Language :: Python :: 3.13
Requires-Dist: boto3 (>=1.36.17,<2.0.0)
Requires-Dist: click (>=8.1.8,<9.0.0)
Requires-Dist: cryptography (>=44.0.2,<45.0.0)
Requires-Dist: pyyaml (>=6.0.2,<7.0.0)
Requires-Dist: zipfile39 (>=0.0.8.0,<0.0.9.0)
Project-URL: Homepage, https://github.com/svange/ope-tools
